{
  "title": "Kana Vocab 39: まあ, マーケット, マイク...",
  "lesson_number": 1345,
  "lesson_type": "kana_vocab",
  "items": [
    {
      "entry_id": 38385,
      "kana": "まあ",
      "gloss": "just (e.g. \"just wait here\"); come now; now, now; tolerably; passably; moderately; reasonably; fairly; rather; somewhat; well...; I think...; it would seem...; you might say...; Hmmm, I guess so...; oh!; oh dear!; oh, my!; wow!; goodness gracious!; good heavens!",
      "card_type": "vocab"
    },
    {
      "entry_id": 54537,
      "kana": "マーケット",
      "gloss": "market",
      "card_type": "vocab"
    },
    {
      "entry_id": 54597,
      "kana": "マイク",
      "gloss": "mike; mic; microphone",
      "card_type": "vocab"
    },
    {
      "entry_id": 54785,
      "kana": "マスター",
      "gloss": "to master (a skill); proprietor; manager; owner; barkeeper; leader; chief; head; master (of arts, science, etc.); master (recording); master (device)",
      "card_type": "vocab"
    },
    {
      "entry_id": 54956,
      "kana": "ママ",
      "gloss": "mama; mamma; mom; mommy; mum; mummy; mother; female proprietress (of a bar, etc.)",
      "card_type": "vocab"
    },
    {
      "entry_id": 117604,
      "kana": "ママ",
      "gloss": "as it is; as one likes; because; as; condition; state; sic; sic erat scriptum; the quoted matter has been transcribed exactly as found in the source text",
      "card_type": "vocab"
    },
    {
      "entry_id": 55134,
      "kana": "ミス",
      "gloss": "mistake; error; failure; Miss; myth",
      "card_type": "vocab"
    }
  ]
}