{
  "title": "Kana Vocab 42: イコール, インキ, インタビュー...",
  "lesson_number": 1348,
  "lesson_type": "kana_vocab",
  "items": [
    {
      "entry_id": 39675,
      "kana": "イコール",
      "gloss": "equal; equivalent; equals sign; equality sign; equals (as in \"A equals B\")",
      "card_type": "vocab"
    },
    {
      "entry_id": 39821,
      "kana": "インキ",
      "gloss": "ink",
      "card_type": "vocab"
    },
    {
      "entry_id": 39939,
      "kana": "インタビュー",
      "gloss": "interview (i.e. television, newspaper, etc.)",
      "card_type": "vocab"
    },
    {
      "entry_id": 40189,
      "kana": "ウーマン",
      "gloss": "woman",
      "card_type": "vocab"
    },
    {
      "entry_id": 40199,
      "kana": "ウール",
      "gloss": "wool",
      "card_type": "vocab"
    },
    {
      "entry_id": 40350,
      "kana": "ウエートレス",
      "gloss": "waitress",
      "card_type": "vocab"
    },
    {
      "entry_id": 36325,
      "kana": "うっかり",
      "gloss": "carelessly; thoughtlessly; inadvertently",
      "card_type": "vocab"
    }
  ]
}