{
  "source_file": "Spoonfed Japanese Kana Lessons 1-32.ods",
  "items": [
    {
      "entry_id": 325414,
      "kanji": null,
      "kana": "パ",
      "gloss": "pa"
    },
    {
      "entry_id": 325313,
      "kanji": null,
      "kana": "ピ",
      "gloss": "pi"
    },
    {
      "entry_id": 325314,
      "kanji": null,
      "kana": "プ",
      "gloss": "pu"
    },
    {
      "entry_id": 325315,
      "kanji": null,
      "kana": "ペ",
      "gloss": "pe"
    },
    {
      "entry_id": 325316,
      "kanji": null,
      "kana": "ポ",
      "gloss": "po"
    }
  ]
}