{
  "title": "Lesson 282: 下げる, 差し上げる, 殺気...",
  "lesson_number": 282,
  "jlpt_level": "N4",
  "items": [
    {
      "entry_id": 62396,
      "kanji": "下げる",
      "kana": "さげる",
      "gloss": "to hang; to suspend; to wear (e.g. decoration); to lower; to reduce; to bring down; to demote; to move back; to pull back; to clear (plates); to remove (food, etc. from table or altar); to keep on playing after one has formed a scoring combination with captured cards",
      "card_type": "vocab"
    },
    {
      "entry_id": 76346,
      "kanji": "差し上げる",
      "kana": "さしあげる",
      "gloss": "to give; to offer; to lift up; to hold up; to raise",
      "card_type": "vocab"
    },
    {
      "entry_id": 77359,
      "kanji": "殺気",
      "kana": "さっき",
      "gloss": "thirst for blood; bloodlust; determination to kill",
      "card_type": "vocab"
    },
    {
      "entry_id": 87271,
      "kanji": "数奇",
      "kana": "さっき",
      "gloss": "misfortune; adverse fortune; hapless fate; checkered (life, career, etc.); varied; eventful; dramatic; full of ups and downs",
      "card_type": "vocab"
    },
    {
      "entry_id": 285297,
      "kanji": "昨季",
      "kana": "さっき",
      "gloss": "last season (e.g. in sports); equivalent season last year",
      "card_type": "vocab"
    },
    {
      "entry_id": 314071,
      "kanji": "削器",
      "kana": "さっき",
      "gloss": "(stone) scraper",
      "card_type": "vocab"
    },
    {
      "entry_id": 115999,
      "kanji": "寂しい",
      "kana": "さびしい",
      "gloss": "lonely; lonesome; solitary; desolate",
      "card_type": "vocab"
    }
  ]
}