{
  "title": "Lesson 987: 見地, 賢明, 倹約...",
  "lesson_number": 987,
  "jlpt_level": "N1",
  "items": [
    {
      "entry_id": 72249,
      "kanji": "見地",
      "kana": "けんち",
      "gloss": "point of view",
      "card_type": "vocab"
    },
    {
      "entry_id": 72311,
      "kanji": "賢明",
      "kana": "けんめい",
      "gloss": "wise; sensible; well-advised; intelligent; sagacious; prudent",
      "card_type": "vocab"
    },
    {
      "entry_id": 71750,
      "kanji": "倹約",
      "kana": "けんやく",
      "gloss": "thrift; economy; frugality",
      "card_type": "vocab"
    },
    {
      "entry_id": 71826,
      "kanji": "兼用",
      "kana": "けんよう",
      "gloss": "multi-use; combined use; combination; serving two purposes",
      "card_type": "vocab"
    },
    {
      "entry_id": 72018,
      "kanji": "権力",
      "kana": "けんりょく",
      "gloss": "(political) power; authority; influence",
      "card_type": "vocab"
    },
    {
      "entry_id": 71398,
      "kanji": "劇団",
      "kana": "げきだん",
      "gloss": "troupe; theatrical company",
      "card_type": "vocab"
    },
    {
      "entry_id": 71434,
      "kanji": "激励",
      "kana": "げきれい",
      "gloss": "encouragement; spurring (on); cheering (on)",
      "card_type": "vocab"
    }
  ]
}