{
  "title": "Lesson 1169: 同感, 動機, 同級...",
  "lesson_number": 1169,
  "jlpt_level": "N1",
  "items": [
    {
      "entry_id": 97846,
      "kanji": "同感",
      "kana": "どうかん",
      "gloss": "same feeling; same sentiment; same opinion; sympathy; agreement; concurrence",
      "card_type": "vocab"
    },
    {
      "entry_id": 97770,
      "kanji": "動機",
      "kana": "どうき",
      "gloss": "motive; incentive; motif",
      "card_type": "vocab"
    },
    {
      "entry_id": 97855,
      "kanji": "同級",
      "kana": "どうきゅう",
      "gloss": "the same grade; same class",
      "card_type": "vocab"
    },
    {
      "entry_id": 97857,
      "kanji": "同居",
      "kana": "どうきょ",
      "gloss": "coexistence; living together",
      "card_type": "vocab"
    },
    {
      "entry_id": 97772,
      "kanji": "動向",
      "kana": "どうこう",
      "gloss": "trend; tendency; movement; attitude",
      "card_type": "vocab"
    },
    {
      "entry_id": 97885,
      "kanji": "同士",
      "kana": "どうし",
      "gloss": "fellow; mutual; companion; comrade",
      "card_type": "vocab"
    },
    {
      "entry_id": 97887,
      "kanji": "同志",
      "kana": "どうし",
      "gloss": "like-mindedness; (being of the) same mind; shared sentiment; comrade; fellow; kindred soul",
      "card_type": "vocab"
    }
  ]
}