{
  "title": "Lesson 1105: その上, その外, 其の儘...",
  "lesson_number": 1105,
  "jlpt_level": "N1",
  "items": [
    {
      "entry_id": 267206,
      "kanji": "その上",
      "kana": "そのかみ",
      "gloss": "a long time ago; in those days; once upon a time",
      "card_type": "vocab"
    },
    {
      "entry_id": 37491,
      "kanji": "その外",
      "kana": "そのた",
      "gloss": "the rest; the others; in addition (to that); besides that; other than that; and other ...; and so forth; and the like; and what have you; et cetera",
      "card_type": "vocab"
    },
    {
      "entry_id": 91788,
      "kanji": "其の儘",
      "kana": "そのまんま",
      "gloss": "without change; as is; just like; extremely similar; immediately; just after; without a pause",
      "card_type": "vocab"
    },
    {
      "entry_id": 113701,
      "kanji": "聳える",
      "kana": "そびえる",
      "gloss": "to rise; to tower; to soar",
      "card_type": "vocab"
    },
    {
      "entry_id": 90580,
      "kanji": "素朴",
      "kana": "そぼく",
      "gloss": "simple; artless; naive; unsophisticated",
      "card_type": "vocab"
    },
    {
      "entry_id": 89744,
      "kanji": "染まる",
      "kana": "そまる",
      "gloss": "to be dyed; to be tainted; to be infected; to be stained; to be steeped",
      "card_type": "vocab"
    },
    {
      "entry_id": 100607,
      "kanji": "背く",
      "kana": "そむく",
      "gloss": "to run counter to; to go against; to disobey; to infringe",
      "card_type": "vocab"
    }
  ]
}