{
  "title": "Lesson 933: 固める, 偏る, 傍ら...",
  "lesson_number": 933,
  "jlpt_level": "N1",
  "items": [
    {
      "entry_id": 73159,
      "kanji": "固める",
      "kana": "かためる",
      "gloss": "to harden; to freeze; to strengthen; to solidify; to make (a fist); to tramp down (snow, dirt); to put together; to collect; to gather; to consolidate; to make secure; to stabilize; to settle down; to strengthen (belief, resolution, etc.); to establish (evidence); to fortify; to reinforce; to support; to wear for a specific purpose (armor, coat, etc.); to swear; to resolutely vow; to sincerely promise; to tie tightly; to fasten; to hold a bow fully drawn",
      "card_type": "vocab"
    },
    {
      "entry_id": 119119,
      "kanji": "偏る",
      "kana": "かたよる",
      "gloss": "to lean (to one side); to incline; to be unbalanced (e.g. diet); to be unduly weighted towards; to be concentrated on; to be partial; to be biased; to be prejudiced",
      "card_type": "vocab"
    },
    {
      "entry_id": 119124,
      "kanji": "傍ら",
      "kana": "かたわら",
      "gloss": "side; edge; beside; besides; nearby; while (doing); in addition to; at the same time",
      "card_type": "vocab"
    },
    {
      "entry_id": 63895,
      "kanji": "課題",
      "kana": "かだい",
      "gloss": "subject; theme; issue; matter; homework; assignment; task; challenge; problem; question",
      "card_type": "vocab"
    },
    {
      "entry_id": 119132,
      "kanji": "花壇",
      "kana": "かだん",
      "gloss": "flower bed",
      "card_type": "vocab"
    },
    {
      "entry_id": 63380,
      "kanji": "家畜",
      "kana": "かちく",
      "gloss": "domestic animals; livestock; cattle",
      "card_type": "vocab"
    },
    {
      "entry_id": 64110,
      "kanji": "画期",
      "kana": "かっき",
      "gloss": "transition from one epoch to another; change of era",
      "card_type": "vocab"
    }
  ]
}