{
  "title": "Lesson 1295: 理性, 利息, 立体...",
  "lesson_number": 1295,
  "jlpt_level": "N1",
  "items": [
    {
      "entry_id": 110732,
      "kanji": "理性",
      "kana": "りせい",
      "gloss": "reason; reasoning power; (one's) sense",
      "card_type": "vocab"
    },
    {
      "entry_id": 110674,
      "kanji": "利息",
      "kana": "りそく",
      "gloss": "interest (on a loan, deposit, etc.)",
      "card_type": "vocab"
    },
    {
      "entry_id": 110970,
      "kanji": "立体",
      "kana": "りったい",
      "gloss": "solid body; three-dimensional object; multi-storey car park",
      "card_type": "vocab"
    },
    {
      "entry_id": 110981,
      "kanji": "立法",
      "kana": "りっぽう",
      "gloss": "legislation; lawmaking",
      "card_type": "vocab"
    },
    {
      "entry_id": 110676,
      "kanji": "利点",
      "kana": "りてん",
      "gloss": "advantage; point in favor; point in favour",
      "card_type": "vocab"
    },
    {
      "entry_id": 111000,
      "kanji": "略語",
      "kana": "りゃくご",
      "gloss": "abbreviation; acronym",
      "card_type": "vocab"
    },
    {
      "entry_id": 123764,
      "kanji": "略奪",
      "kana": "りゃくだつ",
      "gloss": "pillage; plunder; looting; robbery",
      "card_type": "vocab"
    }
  ]
}